casrel_datautils/Base_Conf.py
casrel_datautils/__init__.py
casrel_datautils/casrel_model.py
casrel_datautils/data_loader.py
casrel_datautils/new_data_processor.py
casrel_datautils/process.py
mypacksuperlyl-1.1.5.dist-info/licenses/License
tests/__init__.py
tests/tools_demo_已测.py
mypacksuperlyl-1.1.5.dist-info/METADATA
mypacksuperlyl-1.1.5.dist-info/WHEEL
mypacksuperlyl-1.1.5.dist-info/top_level.txt
mypacksuperlyl-1.1.5.dist-info/RECORD
